scandeavour/__main__.py
scandeavour/ingestor_base.py
scandeavour/setup_database.sqlite
scandeavour/utils.py
scandeavour/assets/bootstrap.min.css
scandeavour/assets/dashAGGridFunctions.js
scandeavour/assets/patchFileReader.js
scandeavour/assets/css/appstyle.css
scandeavour/assets/css/datastyle.css
scandeavour/assets/css/graphstyle.css
scandeavour/assets/css/importstyle.css
scandeavour/assets/css/statsstyle.css
scandeavour/assets/icons/coffee.svg
scandeavour/assets/icons/graph.svg
scandeavour/assets/icons/hexagon.svg
scandeavour/assets/icons/import.svg
scandeavour/assets/icons/pie-chart.svg
scandeavour/assets/icons/stats.svg
scandeavour/assets/icons/upload-file.svg
scandeavour/assets/icons/datapage/filter-close.svg
scandeavour/assets/icons/datapage/export/clipboard.svg
scandeavour/assets/icons/datapage/export/download.svg
scandeavour/assets/icons/graphpage/box-off.svg
scandeavour/assets/icons/graphpage/box-on.svg
scandeavour/assets/icons/graphpage/box.svg
scandeavour/assets/icons/graphpage/crosshair.svg
scandeavour/assets/icons/graphpage/datafilter-off.svg
scandeavour/assets/icons/graphpage/datafilter-on.svg
scandeavour/assets/icons/graphpage/filter.svg
scandeavour/assets/icons/graphpage/host-off.svg
scandeavour/assets/icons/graphpage/host-on.svg
scandeavour/assets/icons/graphpage/host.svg
scandeavour/assets/icons/graphpage/maximize.svg
scandeavour/assets/icons/graphpage/terminal-off.svg
scandeavour/assets/icons/graphpage/terminal-on.svg
scandeavour/assets/icons/graphpage/terminal.svg
scandeavour/assets/icons/graphpage/trash.svg
scandeavour/assets/icons/headings/cpu.svg
scandeavour/assets/icons/headings/filter.svg
scandeavour/assets/icons/headings/grid.svg
scandeavour/assets/icons/headings/list.svg
scandeavour/assets/icons/headings/listitem.svg
scandeavour/assets/icons/headings/pocket.svg
scandeavour/assets/icons/headings/tool.svg
scandeavour/assets/icons/host-details/activity.svg
scandeavour/assets/icons/host-details/box.svg
scandeavour/assets/icons/node-info/activity.svg
scandeavour/assets/icons/node-info/bookmark.svg
scandeavour/assets/icons/node-info/chevron-left.svg
scandeavour/assets/icons/node-info/chevron-right.svg
scandeavour/assets/icons/node-info/compass.svg
scandeavour/assets/icons/node-info/cpu.svg
scandeavour/assets/icons/node-info/file-text.svg
scandeavour/assets/icons/node-info/git-branch.svg
scandeavour/assets/icons/node-info/home.svg
scandeavour/assets/icons/node-info/info.svg
scandeavour/assets/icons/node-info/link.svg
scandeavour/assets/icons/node-info/list.svg
scandeavour/assets/icons/node-info/pie-chart.svg
scandeavour/assets/icons/node-info/play-circle.svg
scandeavour/assets/icons/node-info/repeat.svg
scandeavour/assets/icons/node-info/stop-circle.svg
scandeavour/assets/icons/node-info/tool.svg
scandeavour/assets/icons/node-info/trello.svg
scandeavour-1.3.2.dist-info/licenses/LICENSE
scandeavour-1.3.2.dist-info/METADATA
scandeavour-1.3.2.dist-info/WHEEL
scandeavour-1.3.2.dist-info/entry_points.txt
scandeavour-1.3.2.dist-info/top_level.txt
scandeavour-1.3.2.dist-info/RECORD
