Metadata-Version: 2.4
Name: scandeavour
Version: 1.3.2
Summary: Dashboard for merging, visualising and filtering network scans
Author-email: cr4ckc4t <cr4ckc4t@github.com>
Project-URL: Homepage, https://github.com/Cr4ckC4t/scandeavour
Keywords: nmap,nessus,dashboard
Classifier: Programming Language :: Python
Classifier: Programming Language :: Python :: 3
Requires-Python: >=3.12
License-File: LICENSE
Requires-Dist: dash>=2.18.1
Requires-Dist: dash[diskcache]
Requires-Dist: dash-bootstrap-components>=1.6.0
Requires-Dist: dash_ag_grid>=31.2.0
Requires-Dist: dash_cytoscape>=1.0.2
Provides-Extra: dev
Requires-Dist: bumpver; extra == "dev"
Dynamic: license-file
